LICENSE
pylint_exception_var_name_plugin/__init__.py
pylint_exception_var_name_plugin/checker.py
pylint_exception_var_name_plugin/exception_var_name.py
pylint_exception_var_name_plugin-0.1.3.dist-info/LICENSE
pylint_exception_var_name_plugin-0.1.3.dist-info/METADATA
pylint_exception_var_name_plugin-0.1.3.dist-info/WHEEL
pylint_exception_var_name_plugin-0.1.3.dist-info/RECORD
